selenium_driver_initializer/__init__.py
selenium_driver_initializer/init_dc.py
selenium_driver_initializer-0.0.1.dist-info/LICENSE
selenium_driver_initializer-0.0.1.dist-info/METADATA
selenium_driver_initializer-0.0.1.dist-info/WHEEL
selenium_driver_initializer-0.0.1.dist-info/top_level.txt
selenium_driver_initializer-0.0.1.dist-info/RECORD
