Metadata-Version: 2.1
Name: selenium_driver_initializer
Version: 0.0.1
Summary: A Python package to initialize Selenium WebDriver with custom configurations.
Home-page: https://github.com/ZeeshanAhmed95/selenium-driver-initializerPKG
Author: Zeeshan Ahmed
Author-email: zeeshanaliahmed@gmail.com
License-File: LICENSE
Requires-Dist: selenium
Requires-Dist: requests
